LICENSE
markdown_toolkit/__init__.py
markdown_toolkit/constants.py
markdown_toolkit/document.py
markdown_toolkit/injector.py
markdown_toolkit/utils.py
markdown_toolkit-0.3.0.dist-info/LICENSE
markdown_toolkit-0.3.0.dist-info/WHEEL
markdown_toolkit-0.3.0.dist-info/METADATA
markdown_toolkit-0.3.0.dist-info/RECORD
