Metadata-Version: 2.1
Name: markdown-toolkit
Version: 0.3.0
Summary: Utility package for programmatically manipulating markdown documents.
Home-page: https://github.com/danielloader/markdown-toolkit/
License: MIT
Keywords: markdown
Author: Daniel Loader
Author-email: hello@danielloader.uk
Requires-Python: >=3.7,<4.0
Classifier: License :: OSI Approved :: MIT License
Classifier: Programming Language :: Python :: 3
Classifier: Programming Language :: Python :: 3.7
Classifier: Programming Language :: Python :: 3.8
Classifier: Programming Language :: Python :: 3.9
Classifier: Programming Language :: Python :: 3.10
Project-URL: Repository, https://github.com/danielloader/markdown-toolkit/
